setup.py
fbmsgbot/__init__.py
fbmsgbot/bot.py
fbmsgbot/http_client.py
fbmsgbot.egg-info/PKG-INFO
fbmsgbot.egg-info/SOURCES.txt
fbmsgbot.egg-info/dependency_links.txt
fbmsgbot.egg-info/top_level.txt
fbmsgbot/models/__init__.py
fbmsgbot/models/attachment.py
fbmsgbot/models/message.py
fbmsgbot/resources/__init__.py
fbmsgbot/resources/urls.py