Metadata-Version: 1.1
Name: fbmsgbot
Version: 0.1.7
Summary: Python bot for Facebook Messenger
Home-page: https://github.com/ben-cunningham/pybot
Author: Benjamin Cunningham & Austin Hendy
Author-email: bencunningham17@gmail.com
License: UNKNOWN
Download-URL: https://github.com/ben-cunningham/pybot/tarball/0.1.7
Platform: UNKNOWN
